chromatica-0.1.0.dist-info/licenses/LICENSE
conversions/__init__.py
conversions/to_hsl.py
conversions/to_hsv.py
conversions/to_rgb.py
conversions/unit_float.py
conversions/utils.py
conversions/wrapper.py
chromatica-0.1.0.dist-info/METADATA
chromatica-0.1.0.dist-info/WHEEL
chromatica-0.1.0.dist-info/top_level.txt
chromatica-0.1.0.dist-info/RECORD
