Metadata-Version: 2.4
Name: chromatica
Version: 0.1.0
Summary: Advanced color manipulation library for gradients and conversions
Author-email: Grayjou <cgrayjou@gmail.com>
License: MIT
Project-URL: Homepage, https://github.com/Grayjou/chromatica
Project-URL: Repository, https://github.com/Grayjou/chromatica
Project-URL: Issues, https://github.com/Grayjou/chromatica/issues
Classifier: Development Status :: 4 - Beta
Classifier: Intended Audience :: Developers
Classifier: License :: OSI Approved :: MIT License
Classifier: Programming Language :: Python :: 3.8
Classifier: Programming Language :: Python :: 3.9
Classifier: Programming Language :: Python :: 3.10
Classifier: Programming Language :: Python :: 3.11
Classifier: Topic :: Multimedia :: Graphics
Requires-Python: >=3.8
License-File: LICENSE
Requires-Dist: numpy>=1.21.0
Requires-Dist: pillow>=9.0.0
Requires-Dist: scikit-image>=0.19.0
Provides-Extra: dev
Requires-Dist: pytest>=7.0; extra == "dev"
Requires-Dist: twine>=4.0; extra == "dev"
Requires-Dist: coverage>=6.0; extra == "dev"
Dynamic: license-file
